agent_airlock/__init__.py
agent_airlock/audit.py
agent_airlock/audit_otel.py
agent_airlock/capabilities.py
agent_airlock/circuit_breaker.py
agent_airlock/config.py
agent_airlock/context.py
agent_airlock/conversation.py
agent_airlock/core.py
agent_airlock/cost_tracking.py
agent_airlock/filesystem.py
agent_airlock/honeypot.py
agent_airlock/mcp.py
agent_airlock/mcp_proxy_guard.py
agent_airlock/network.py
agent_airlock/observability.py
agent_airlock/policy.py
agent_airlock/py.typed
agent_airlock/retry.py
agent_airlock/safe_types.py
agent_airlock/sandbox.py
agent_airlock/sandbox_backend.py
agent_airlock/sanitizer.py
agent_airlock/self_heal.py
agent_airlock/streaming.py
agent_airlock/testing.py
agent_airlock/unknown_args.py
agent_airlock/vaccine.py
agent_airlock/validator.py
agent_airlock/cli/__init__.py
agent_airlock/cli/doctor.py
agent_airlock/cli/verify.py
agent_airlock/integrations/__init__.py
agent_airlock/integrations/anthropic.py
agent_airlock/integrations/langchain.py
agent_airlock/integrations/openai_guardrails.py
agent_airlock-0.4.0.dist-info/METADATA
agent_airlock-0.4.0.dist-info/WHEEL
agent_airlock-0.4.0.dist-info/licenses/LICENSE
agent_airlock-0.4.0.dist-info/RECORD
