Metadata-Version: 2.4
Name: agent-airlock
Version: 0.4.0
Summary: The Pydantic-based Firewall for MCP Servers. Stops hallucinated tool calls, validates schemas, and sandboxes dangerous operations.
Project-URL: Homepage, https://github.com/sattyamjain/agent-airlock
Project-URL: Documentation, https://github.com/sattyamjain/agent-airlock#readme
Project-URL: Repository, https://github.com/sattyamjain/agent-airlock
Project-URL: Issues, https://github.com/sattyamjain/agent-airlock/issues
Author-email: Sattyam Jain <sattyamjain@example.com>
License-Expression: MIT
License-File: LICENSE
Keywords: agent-safety,ai-security,e2b,llm,mcp,model-context-protocol,pydantic,sandbox,validation
Classifier: Development Status :: 4 - Beta
Classifier: Intended Audience :: Developers
Classifier: License :: OSI Approved :: MIT License
Classifier: Operating System :: OS Independent
Classifier: Programming Language :: Python :: 3
Classifier: Programming Language :: Python :: 3.10
Classifier: Programming Language :: Python :: 3.11
Classifier: Programming Language :: Python :: 3.12
Classifier: Topic :: Security
Classifier: Topic :: Software Development :: Libraries :: Python Modules
Classifier: Typing :: Typed
Requires-Python: >=3.10
Requires-Dist: pydantic<3.0,>=2.0
Requires-Dist: structlog>=24.0
Requires-Dist: tomli>=2.0; python_version < '3.11'
Provides-Extra: all
Requires-Dist: cloudpickle>=3.0; extra == 'all'
Requires-Dist: e2b<2.0,>=1.0; extra == 'all'
Requires-Dist: fastmcp<3.0,>=2.0; extra == 'all'
Requires-Dist: mcp>=1.0; extra == 'all'
Provides-Extra: dev
Requires-Dist: bandit>=1.7; extra == 'dev'
Requires-Dist: cyclonedx-bom>=4.0; extra == 'dev'
Requires-Dist: mypy>=1.8; extra == 'dev'
Requires-Dist: pytest-asyncio>=0.23; extra == 'dev'
Requires-Dist: pytest-benchmark>=4.0; extra == 'dev'
Requires-Dist: pytest-cov>=4.0; extra == 'dev'
Requires-Dist: pytest>=8.0; extra == 'dev'
Requires-Dist: ruff>=0.2; extra == 'dev'
Requires-Dist: safety>=3.0; extra == 'dev'
Provides-Extra: docs
Requires-Dist: mkdocs-material>=9.5; extra == 'docs'
Requires-Dist: mkdocs>=1.5; extra == 'docs'
Requires-Dist: mkdocstrings[python]>=0.24; extra == 'docs'
Requires-Dist: pymdown-extensions>=10.0; extra == 'docs'
Provides-Extra: mcp
Requires-Dist: fastmcp<3.0,>=2.0; extra == 'mcp'
Requires-Dist: mcp>=1.0; extra == 'mcp'
Provides-Extra: sandbox
Requires-Dist: cloudpickle>=3.0; extra == 'sandbox'
Requires-Dist: e2b<2.0,>=1.0; extra == 'sandbox'
